poly2graph/CharPolyClass.py
poly2graph/SpectralGraph.py
poly2graph/__init__.py
poly2graph/hamiltonian.py
poly2graph/skeleton2graph.py
poly2graph/spectral_graph.py
poly2graph/util.py
poly2graph/vis.py
poly2graph-0.2.1.dist-info/METADATA
poly2graph-0.2.1.dist-info/WHEEL
poly2graph-0.2.1.dist-info/licenses/LICENSE
poly2graph-0.2.1.dist-info/RECORD
