Metadata-Version: 2.4
Name: poly2graph
Version: 0.2.1
Summary: Automated Non-Hermitian Spectral Graph Construction
Project-URL: Homepage, https://github.com/sarinstein-yan/poly2graph
Project-URL: Repository, https://github.com/sarinstein-yan/poly2graph
Author-email: "Xianquan (Sarinstein) Yan" <xianquanyan@gmail.com>, Hakan Akgün <hakanakgun317@gmail.com>
Maintainer-email: "Xianquan (Sarinstein) Yan" <xianquanyan@gmail.com>
License: MIT License
License-File: LICENSE
Keywords: Hamiltonian spectral graph,algebraic geometry,computer vision,graph representation learning,morphological image processing,non-bloch band,non-hermitian spectral graph
Classifier: Development Status :: 3 - Alpha
Classifier: Environment :: GPU :: NVIDIA CUDA
Classifier: Intended Audience :: Science/Research
Classifier: License :: OSI Approved :: MIT License
Classifier: Programming Language :: Python :: 3 :: Only
Classifier: Programming Language :: Python :: 3.11
Classifier: Programming Language :: Python :: 3.12
Classifier: Programming Language :: Python :: 3.13
Requires-Python: >=3.11
Requires-Dist: matplotlib
Requires-Dist: networkx
Requires-Dist: numba
Requires-Dist: numpy
Requires-Dist: scikit-image
Requires-Dist: scikit-learn
Requires-Dist: sympy
Provides-Extra: dev
Requires-Dist: jupyter; extra == 'dev'
Requires-Dist: tensorflow; extra == 'dev'
